aibs_informatics_cdk_lib/__init__.py
aibs_informatics_cdk_lib/_version.py
aibs_informatics_cdk_lib/py.typed
aibs_informatics_cdk_lib/cicd/__init__.py
aibs_informatics_cdk_lib/cicd/target.py
aibs_informatics_cdk_lib/cicd/pipeline/__init__.py
aibs_informatics_cdk_lib/cicd/pipeline/base.py
aibs_informatics_cdk_lib/cicd/pipeline/scripts/cicd-release.sh
aibs_informatics_cdk_lib/common/__init__.py
aibs_informatics_cdk_lib/common/git.py
aibs_informatics_cdk_lib/common/aws/__init__.py
aibs_informatics_cdk_lib/common/aws/core_utils.py
aibs_informatics_cdk_lib/common/aws/iam_utils.py
aibs_informatics_cdk_lib/common/aws/sfn_utils.py
aibs_informatics_cdk_lib/constructs_/__init__.py
aibs_informatics_cdk_lib/constructs_/base.py
aibs_informatics_cdk_lib/constructs_/external_sns_trigger.py
aibs_informatics_cdk_lib/constructs_/monitoring.py
aibs_informatics_cdk_lib/constructs_/assets/__init__.py
aibs_informatics_cdk_lib/constructs_/assets/code_asset.py
aibs_informatics_cdk_lib/constructs_/assets/code_asset_definitions.py
aibs_informatics_cdk_lib/constructs_/batch/__init__.py
aibs_informatics_cdk_lib/constructs_/batch/defaults.py
aibs_informatics_cdk_lib/constructs_/batch/infrastructure.py
aibs_informatics_cdk_lib/constructs_/batch/instance_types.py
aibs_informatics_cdk_lib/constructs_/batch/launch_template.py
aibs_informatics_cdk_lib/constructs_/batch/monitoring.py
aibs_informatics_cdk_lib/constructs_/batch/types.py
aibs_informatics_cdk_lib/constructs_/cw/__init__.py
aibs_informatics_cdk_lib/constructs_/cw/dashboard.py
aibs_informatics_cdk_lib/constructs_/cw/types.py
aibs_informatics_cdk_lib/constructs_/cw/config_generators/__init__.py
aibs_informatics_cdk_lib/constructs_/cw/config_generators/lambda_.py
aibs_informatics_cdk_lib/constructs_/cw/config_generators/sfn.py
aibs_informatics_cdk_lib/constructs_/dynamodb/__init__.py
aibs_informatics_cdk_lib/constructs_/dynamodb/table.py
aibs_informatics_cdk_lib/constructs_/ec2/__init__.py
aibs_informatics_cdk_lib/constructs_/ec2/network.py
aibs_informatics_cdk_lib-0.8.1.dist-info/licenses/LICENSE
aibs_informatics_cdk_lib-0.8.1.dist-info/METADATA
aibs_informatics_cdk_lib-0.8.1.dist-info/WHEEL
aibs_informatics_cdk_lib-0.8.1.dist-info/top_level.txt
aibs_informatics_cdk_lib-0.8.1.dist-info/RECORD
