Metadata-Version: 2.4
Name: aibs-informatics-cdk-lib
Version: 0.8.1
Summary: CDK Library for AIBS Informatics services
Author-email: AIBS Informatics Group <marmot@alleninstitute.onmicrosoft.com>
Maintainer-email: AIBS Informatics Group <marmot@alleninstitute.onmicrosoft.com>
License: Allen Institute Software License – This software license is the 2-clause BSD 
Project-URL: Documentation, https://.github.io/aibs-informatics-cdk-lib/
Project-URL: Homepage, https://github.com/AllenInstitute/aibs-informatics-cdk-lib/
Project-URL: Issues, https://github.com/AllenInstitute/aibs-informatics-cdk-lib/issues
Project-URL: Repository, https://github.com/AllenInstitute/aibs-informatics-cdk-lib/
Requires-Python: >=3.9
License-File: LICENSE
Requires-Dist: aibs-informatics-aws-utils<1.0,>=0.0.12
Requires-Dist: aibs-informatics-core~=0.1
Requires-Dist: aws-cdk-lib~=2.96
Requires-Dist: constructs~=10.0
Requires-Dist: pydantic~=2.0
Provides-Extra: dev
Requires-Dist: aibs-informatics-test-resources[all]~=0.0.4; extra == "dev"
Requires-Dist: boto3-stubs[batch,s3]; extra == "dev"
Requires-Dist: mypy~=1.13.0; extra == "dev"
Provides-Extra: release
Requires-Dist: build; extra == "release"
Requires-Dist: bump-my-version; extra == "release"
Requires-Dist: wheel; extra == "release"
Dynamic: license-file
